aidantic/__init__.py
aidantic/aidantic.py
Aidantic-1.0.1.dist-info/METADATA
Aidantic-1.0.1.dist-info/WHEEL
Aidantic-1.0.1.dist-info/top_level.txt
Aidantic-1.0.1.dist-info/RECORD
