Metadata-Version: 2.1
Name: Aidantic
Version: 1.0.1
Summary: Data parsing and validation with OneOf using Python type hints
Home-page: https://github.com/AivanF/Aidantic
Author: AivanF.
Author-email: projects@aivanf.com
License: UNKNOWN
Platform: UNKNOWN
Classifier: Development Status :: 4 - Beta
Classifier: Programming Language :: Python :: 3
Classifier: Operating System :: OS Independent
Classifier: Topic :: Text Processing
Classifier: Topic :: Software Development :: Testing
Classifier: Topic :: Software Development :: Libraries :: Python Modules
Classifier: License :: Freely Distributable
